LICENSE.txt
MANIFEST.in
README.md
VERSION
setup.cfg
setup.py
glutton/__init__.py
glutton.egg-info/PKG-INFO
glutton.egg-info/SOURCES.txt
glutton.egg-info/dependency_links.txt
glutton.egg-info/top_level.txt
glutton/io/__init__.py
glutton/utils/__init__.py
glutton/utils/_inner/__init__.py
glutton/utils/_inner/strutils.py