Metadata-Version: 2.1
Name: glutton
Version: 0.0.1
Summary: glutton
Home-page: https://gitee.com/chaos-god/glutton.git
Author: glutton
Author-email: 9239867+chaos-god@user.noreply.gitee.com
License: UNKNOWN
Platform: UNKNOWN
License-File: LICENSE.txt
